Workbook

Sheet Start Here
A1: Simple Bookkeeping Pack
A2: Built for a growing agro startup — fill in the yellow cells; formulas do the rest
A4: What this is | B4: A set of 9 linked books covering the essentials: cash, sales, purchases, petty cash, inventory, payroll, assets, and debtors/creditors, plus a Monthly Summary that pulls totals automatically.
A5: Where to enter data | B5: Type directly into the row under each example row (shown in blue italics). Delete the blue example row once you're comfortable, or just leave it as a reference — the formulas start from your first real entry.
A6: Colour code | B6: Blue italic text = example row (for reference only). Yellow fill = cells you should edit or check. Everything else recalculates automatically — don't type over formula cells.
A7: Cash Book | B7: Every naira in or out of the business bank/cash account. Balance updates automatically. This is the single most important book — start here.
A8: Sales Book | B8: Every sale made, cash or credit. Amount is calculated automatically from Quantity x Unit Price.
A9: Purchases Book | B9: Every input or item bought — seeds, feed, fertiliser, packaging, equipment.
A10: Petty Cash | B10: Small day-to-day cash expenses (transport, casual labour, minor repairs), kept separate from the main Cash Book.
A11: Inventory Register | B11: Tracks stock — inputs, growing stock, and harvested/finished produce — so nothing quietly goes missing or spoils unrecorded.
A12: Payroll | B12: Wages and salaries paid to staff and farm hands.
A13: Asset Register | B13: Equipment, machinery, vehicles and land improvements, with straight-line depreciation calculated automatically.
A14: Debtors & Creditors | B14: Who owes the business money, and who the business owes — critical if you extend or receive trade credit.
A15: Monthly Summary | B15: Set a start and end date at the top and it pulls totals for that period from every other book automatically. Use it to check monthly performance at a glance.
A16: Recommended rollout | B16: Start with Cash Book, Sales Book, and Purchases Book — these alone will show whether the business is making money. Add Inventory and Payroll once that's routine. Review the Monthly Summary at the end of every month.

Sheet Cash Book
A1: Cash Book
A2: Every naira in and out of the business bank/cash account
A4: Date | B4: Description | C4: Ref/Voucher No | D4: Money In (₦) | E4: Money Out (₦) | F4: Balance (₦)
A5: Opening balance | F5: 250000
A6: 46027 | B6: Sale of maize - Osogbo market | C6: CB-001 | D6: 85000 | E6: 0 | F6: =F5+D6-E6 -> 335000
F7: =F6+D7-E7 -> 335000
F8: =F7+D8-E8 -> 335000
F9: =F8+D9-E9 -> 335000
F10: =F9+D10-E10 -> 335000
F11: =F10+D11-E11 -> 335000
F12: =F11+D12-E12 -> 335000
F13: =F12+D13-E13 -> 335000
F14: =F13+D14-E14 -> 335000
F15: =F14+D15-E15 -> 335000
F16: =F15+D16-E16 -> 335000
F17: =F16+D17-E17 -> 335000
F18: =F17+D18-E18 -> 335000
... F40: =F39+D40-E40 -> 335000

Sheet Sales Book
A1: Sales Book
A2: Every sale made — cash or credit
A4: Date | B4: Customer | C4: Product | D4: Quantity | E4: Unit Price (₦) | F4: Amount (₦) | G4: Payment Status
A5: 46027 | B5: Alaba Foods Ltd | C5: Maize (50kg bags) | D5: 17 | E5: 5000 | F5: =D5*E5 -> 85000 | G5: Cash
F6: =D6*E6 -> 0
F7: =D7*E7 -> 0
F8: =D8*E8 -> 0
F9: =D9*E9 -> 0
F10: =D10*E10 -> 0
F11: =D11*E11 -> 0
F12: =D12*E12 -> 0
F13: =D13*E13 -> 0
F14: =D14*E14 -> 0
F15: =D15*E15 -> 0
F16: =D16*E16 -> 0
F17: =D17*E17 -> 0
... F45: =D45*E45 -> 0
E47: Total Sales | F47: =SUM(F5:F45) -> 85000

Sheet Purchases Book
A1: Purchases Book
A2: Every input or item bought for the business
A4: Date | B4: Supplier | C4: Item | D4: Quantity | E4: Unit Cost (₦) | F4: Amount (₦) | G4: Payment Status
A5: 46025 | B5: Osogbo Agro Supplies | C5: NPK Fertiliser (50kg) | D5: 20 | E5: 12000 | F5: =D5*E5 -> 240000 | G5: Bank Transfer
F6: =D6*E6 -> 0
F7: =D7*E7 -> 0
F8: =D8*E8 -> 0
F9: =D9*E9 -> 0
F10: =D10*E10 -> 0
F11: =D11*E11 -> 0
F12: =D12*E12 -> 0
F13: =D13*E13 -> 0
F14: =D14*E14 -> 0
F15: =D15*E15 -> 0
F16: =D16*E16 -> 0
F17: =D17*E17 -> 0
... F45: =D45*E45 -> 0
E47: Total Purchases | F47: =SUM(F5:F45) -> 240000

Sheet Petty Cash
A1: Petty Cash Book
A2: Small day-to-day cash expenses, kept separate from the main Cash Book
A4: Date | B4: Description | C4: Voucher No | D4: Amount Out (₦) | E4: Balance (₦)
A5: Petty cash float | E5: 20000
A6: 46028 | B6: Transport - delivery to market | C6: PC-001 | D6: 3500 | E6: =E5-D6 -> 16500
E7: =E6-D7 -> 16500
E8: =E7-D8 -> 16500
E9: =E8-D9 -> 16500
E10: =E9-D10 -> 16500
E11: =E10-D11 -> 16500
E12: =E11-D12 -> 16500
E13: =E12-D13 -> 16500
E14: =E13-D14 -> 16500
E15: =E14-D15 -> 16500
E16: =E15-D16 -> 16500
E17: =E16-D17 -> 16500
E18: =E17-D18 -> 16500
... E40: =E39-D40 -> 16500

Sheet Inventory Register
A1: Inventory / Stock Register
A2: Track inputs, growing stock, and harvested or finished produce
A4: Date | B4: Item | C4: Type (Input/Produce) | D4: Unit | E4: Qty In | F4: Qty Out | G4: Balance Qty | H4: Notes
A5: 46025 | B5: NPK Fertiliser | C5: Input | D5: 50kg bags | E5: 20 | F5: 0 | G5: =E5-F5 -> 20 | H5: Delivered by Osogbo Agro Supplies
G6: =G5+E6-F6 -> 20
G7: =G6+E7-F7 -> 20
G8: =G7+E8-F8 -> 20
G9: =G8+E9-F9 -> 20
G10: =G9+E10-F10 -> 20
G11: =G10+E11-F11 -> 20
G12: =G11+E12-F12 -> 20
G13: =G12+E13-F13 -> 20
G14: =G13+E14-F14 -> 20
G15: =G14+E15-F15 -> 20
G16: =G15+E16-F16 -> 20
G17: =G16+E17-F17 -> 20
... G45: =G44+E45-F45 -> 20

Sheet Payroll
A1: Payroll / Wages Book
A2: Wages and salaries paid to staff and farm hands
A4: Date/Period | B4: Staff Name | C4: Role | D4: Days/Hours Worked | E4: Rate (₦) | F4: Amount Paid (₦) | G4: Payment Method
A5: 46053 | B5: Musa Ibrahim | C5: Farm Hand | D5: 24 | E5: 3500 | F5: =D5*E5 -> 84000 | G5: Cash
F6: =D6*E6 -> 0
F7: =D7*E7 -> 0
F8: =D8*E8 -> 0
F9: =D9*E9 -> 0
F10: =D10*E10 -> 0
F11: =D11*E11 -> 0
F12: =D12*E12 -> 0
F13: =D13*E13 -> 0
F14: =D14*E14 -> 0
F15: =D15*E15 -> 0
F16: =D16*E16 -> 0
F17: =D17*E17 -> 0
... F40: =D40*E40 -> 0
E42: Total Payroll | F42: =SUM(F5:F40) -> 84000

Sheet Asset Register
A1: Asset Register
A2: Equipment, machinery, vehicles, and land improvements
A4: Date Acquired | B4: Asset | C4: Description | D4: Cost (₦) | E4: Useful Life (Years) | F4: Annual Depreciation (₦)
A5: 45971 | B5: Water Pump (Petrol) | C5: 2HP irrigation pump | D5: 180000 | E5: 5 | F5: =IFERROR(D5/E5,0) -> 36000
F6: =IFERROR(D6/E6,0) -> 0
F7: =IFERROR(D7/E7,0) -> 0
F8: =IFERROR(D8/E8,0) -> 0
F9: =IFERROR(D9/E9,0) -> 0
F10: =IFERROR(D10/E10,0) -> 0
F11: =IFERROR(D11/E11,0) -> 0
F12: =IFERROR(D12/E12,0) -> 0
F13: =IFERROR(D13/E13,0) -> 0
F14: =IFERROR(D14/E14,0) -> 0
F15: =IFERROR(D15/E15,0) -> 0
F16: =IFERROR(D16/E16,0) -> 0
F17: =IFERROR(D17/E17,0) -> 0
... F30: =IFERROR(D30/E30,0) -> 0

Sheet Debtors & Creditors
A1: Debtors & Creditors Ledger
A2: Who owes the business, and who the business owes
A4: Type | B4: Name | C4: Description | D4: Amount (₦) | E4: Date | F4: Due Date | G4: Status
A5: Debtor | B5: Blessing Stores (Ibadan) | C5: Maize supplied on credit | D5: 150000 | E5: 46032 | F5: 46063 | G5: Outstanding

Sheet Monthly Summary
A1: Monthly Summary
A2: Set the period below — totals pull automatically from every other book
A4: Period Start | B4: 46023
A5: Period End | B5: 46053
A7: Total Sales | B7: =SUMIFS('Sales Book'!F:F,'Sales Book'!A:A,">="&$B$4,'Sales Book'!A:A,"<="&$B$5) -> 85000
A8: Total Purchases | B8: =SUMIFS('Purchases Book'!F:F,'Purchases Book'!A:A,">="&$B$4,'Purchases Book'!A:A,"<="&$B$5) -> 240000
A9: Total Cash In | B9: =SUMIFS('Cash Book'!D:D,'Cash Book'!A:A,">="&$B$4,'Cash Book'!A:A,"<="&$B$5) -> 85000
A10: Total Cash Out | B10: =SUMIFS('Cash Book'!E:E,'Cash Book'!A:A,">="&$B$4,'Cash Book'!A:A,"<="&$B$5) -> 0
A11: Total Payroll Paid | B11: =SUMIFS(Payroll!F:F,Payroll!A:A,">="&$B$4,Payroll!A:A,"<="&$B$5) -> 84000
A12: Total Petty Cash Spent | B12: =SUMIFS('Petty Cash'!D:D,'Petty Cash'!A:A,">="&$B$4,'Petty Cash'!A:A,"<="&$B$5) -> 3500
A14: Net Cash Flow for Period | B14: =B9-B10 -> 85000
A16: Gross Margin (Sales - Purchases) | B16: =B7-B8 -> -155000
